Metadata-Version: 2.1
Name: archetyped
Version: 0.0.1
Summary: Expands further on argetype and other packages
Home-page: https://github.com/dicaso/archetyped
Author: Christophe Van Neste
Author-email: christophe.vanneste@kaust.edu.sa
License: MIT
Platform: UNKNOWN
Requires-Python: >=3.6
Provides-Extra: documentation
